setup.cfg
setup.py
nyaa/__init__.py
nyaa/constants.py
nyaa/nyaa.py
nyaa.egg-info/PKG-INFO
nyaa.egg-info/SOURCES.txt
nyaa.egg-info/dependency_links.txt
nyaa.egg-info/requires.txt
nyaa.egg-info/top_level.txt